{
  "version": "1.0",
  "last_updated": "2025-01-21",
  "mcq_sets": [
    {
      "id": "mcq_math_10_ch2",
      "title": "Real Numbers - Quick Test",
      "subject": "Mathematics",
      "class_number": 10,
      "total_questions": 10,
      "time_limit": 10,
      "difficulty": "Easy",
      "thumbnail": "",
      "questions": [
        {
    "id": "q1",
    "question": "According to Vladimir Arnold, proofs are to mathematics what _________ is to poetry.",
    "options": [
      "Grammar",
      "Rhyme",
      "Calligraphy",
      "Rhythm"
    ],
    "correct_answer": 3,
    "hint": "Compare the artistic structure of characters in a poem to the structure of a mathematical work.",
    "explanation": "The text quotes Vladimir Arnold: \"Proofs are to Mathematics what calligraphy is to poetry\"."
  },
  {
    "id": "q2",
    "question": "A proof of a mathematical statement consists of a sequence of statements where each is justified by:",
    "options": [
      "A hypothesis or a guess",
      "A definition, axiom, or previously established proposition",
      "Experimental data and observation",
      "A counter example"
    ],
    "correct_answer": 2,
    "hint": "Think about the chain of deductive arguments.",
    "explanation": "A proof consists of a sequence of statements, each justified with a definition, an axiom, or a proposition that is previously established."
  },
  {
    "id": "q3",
    "question": "In a direct proof, how does the process begin?",
    "options": [
      "By assuming the conclusion is false",
      "By splitting the statement into multiple cases",
      "By starting directly with what is given in the proposition",
      "By finding an example where the statement fails"
    ],
    "correct_answer": 3,
    "hint": "The name \"Direct Proof\" implies a straightforward approach.",
    "explanation": "In a Direct Proof, we directly start the proof with what is given in the proposition."
  },
  {
    "id": "q4",
    "question": "In Example 1, to prove \"if x²−5x+6=0, then x=3 or x=2\", which algebraic method is initially used?",
    "options": [
      "The quadratic formula",
      "Factorization",
      "Completing the square",
      "Differentiation"
    ],
    "correct_answer": 2,
    "hint": "The equation is transformed into (x−3)(x−2)=0.",
    "explanation": "The text states the first step is proved by factorization: x²−5x+6=(x−3)(x−2)."
  },
  {
    "id": "q5",
    "question": "When proving the function f(x)=2x+5 is one-one using a direct method, what is the starting assumption?",
    "options": [
      "x₁ ≠ x₂",
      "f(x₁)=f(x₂)",
      "f(x₁) ≠ f(x₂)",
      "x₁ = x₂"
    ],
    "correct_answer": 2,
    "hint": "The definition of a one-one function dictates the starting premise.",
    "explanation": "The proof begins with the given that f(x₁)=f(x₂) and deduces that x₁=x₂."
  },
  {
    "id": "q6",
    "question": "Mathematical Induction depends on an axiom related to a subset S of natural numbers N. Which condition must be met first?",
    "options": [
      "The natural number k is in S",
      "The natural number k+1 is in S",
      "The natural number 1 is in S",
      "The set S is finite"
    ],
    "correct_answer": 3,
    "hint": "Induction requires a base case or starting point.",
    "explanation": "The axiom states that the natural number 1 must belong to the set S."
  },
  {
    "id": "q7",
    "question": "In the principle of mathematical induction, if a statement S(n) is true for n=k, we must prove it is true for:",
    "options": [
      "n = k − 1",
      "n = k + 1",
      "n = 2k",
      "n = 1"
    ],
    "correct_answer": 2,
    "hint": "The inductive step moves from one integer to the immediate next.",
    "explanation": "The principle states that if S(n) is true for n=k, then S(n) must be true for n=k+1."
  },
  {
    "id": "q8",
    "question": "In Example 3 involving matrices, to prove P(k+1), the term A^(k+1) is written as:",
    "options": [
      "A^k + A",
      "A^k / A",
      "A^k ⋅ A",
      "A^(k−1) ⋅ A^2"
    ],
    "correct_answer": 3,
    "hint": "Think about the laws of exponents applied to matrix multiplication.",
    "explanation": "The solution states that A^(k+1) = A^k ⋅ A."
  },
  {
    "id": "q9",
    "question": "Proof by cases is a valid method to prove p⇒q only when:",
    "options": [
      "p can be split into cases r, s, t such that p = r ∨ s ∨ t",
      "q can be split into cases r, s, t such that q = r ∨ s ∨ t",
      "The number of cases is infinite",
      "It is impossible to use deductive reasoning"
    ],
    "correct_answer": 1,
    "hint": "The hypothesis must be exhaustive.",
    "explanation": "This method is possible only when p can be split into several exhaustive cases."
  },
  {
    "id": "q10",
    "question": "In Example 4, to prove the projection formula a = bcosC + ccosB, the triangle ABC is split into which three cases?",
    "options": [
      "Isosceles, Scalene, Equilateral",
      "Acute angled, Obtuse angled, Right angled",
      "Small, Medium, Large",
      "Positive area, Negative area, Zero area"
    ],
    "correct_answer": 2,
    "hint": "The classification depends on the angle C.",
    "explanation": "The text splits the proof into cases where angle C is acute, obtuse, or a right angle."
    }
    ]
    },
       {
      "id": "mcq_math_10_ch1",
      "title": "Real Numbers - Quick Test",
      "subject": "Mathematics",
      "class_number": 10,
      "total_questions": 10,
      "time_limit": 10,
      "difficulty": "Easy",
      "thumbnail": "",
      "questions": [
        {
    "id": "q1",
    "question": "According to Vladimir Arnold, proofs are to mathematics what _________ is to poetry.",
    "options": [
      "Grammar",
      "Rhyme",
      "Calligraphy",
      "Rhythm"
    ],
    "correct_answer": 3,
    "hint": "Compare the artistic structure of characters in a poem to the structure of a mathematical work.",
    "explanation": "The text quotes Vladimir Arnold: \"Proofs are to Mathematics what calligraphy is to poetry\"."
  },
  {
    "id": "q2",
    "question": "A proof of a mathematical statement consists of a sequence of statements where each is justified by:",
    "options": [
      "A hypothesis or a guess",
      "A definition, axiom, or previously established proposition",
      "Experimental data and observation",
      "A counter example"
    ],
    "correct_answer": 2,
    "hint": "Think about the chain of deductive arguments.",
    "explanation": "A proof consists of a sequence of statements, each justified with a definition, an axiom, or a proposition that is previously established."
  },
  {
    "id": "q3",
    "question": "In a direct proof, how does the process begin?",
    "options": [
      "By assuming the conclusion is false",
      "By splitting the statement into multiple cases",
      "By starting directly with what is given in the proposition",
      "By finding an example where the statement fails"
    ],
    "correct_answer": 3,
    "hint": "The name \"Direct Proof\" implies a straightforward approach.",
    "explanation": "In a Direct Proof, we directly start the proof with what is given in the proposition."
  },
  {
    "id": "q4",
    "question": "In Example 1, to prove \"if x²−5x+6=0, then x=3 or x=2\", which algebraic method is initially used?",
    "options": [
      "The quadratic formula",
      "Factorization",
      "Completing the square",
      "Differentiation"
    ],
    "correct_answer": 2,
    "hint": "The equation is transformed into (x−3)(x−2)=0.",
    "explanation": "The text states the first step is proved by factorization: x²−5x+6=(x−3)(x−2)."
  },
  {
    "id": "q5",
    "question": "When proving the function f(x)=2x+5 is one-one using a direct method, what is the starting assumption?",
    "options": [
      "x₁ ≠ x₂",
      "f(x₁)=f(x₂)",
      "f(x₁) ≠ f(x₂)",
      "x₁ = x₂"
    ],
    "correct_answer": 2,
    "hint": "The definition of a one-one function dictates the starting premise.",
    "explanation": "The proof begins with the given that f(x₁)=f(x₂) and deduces that x₁=x₂."
  },
  {
    "id": "q6",
    "question": "Mathematical Induction depends on an axiom related to a subset S of natural numbers N. Which condition must be met first?",
    "options": [
      "The natural number k is in S",
      "The natural number k+1 is in S",
      "The natural number 1 is in S",
      "The set S is finite"
    ],
    "correct_answer": 3,
    "hint": "Induction requires a base case or starting point.",
    "explanation": "The axiom states that the natural number 1 must belong to the set S."
  },
  {
    "id": "q7",
    "question": "In the principle of mathematical induction, if a statement S(n) is true for n=k, we must prove it is true for:",
    "options": [
      "n = k − 1",
      "n = k + 1",
      "n = 2k",
      "n = 1"
    ],
    "correct_answer": 2,
    "hint": "The inductive step moves from one integer to the immediate next.",
    "explanation": "The principle states that if S(n) is true for n=k, then S(n) must be true for n=k+1."
  },
  {
    "id": "q8",
    "question": "In Example 3 involving matrices, to prove P(k+1), the term A^(k+1) is written as:",
    "options": [
      "A^k + A",
      "A^k / A",
      "A^k ⋅ A",
      "A^(k−1) ⋅ A^2"
    ],
    "correct_answer": 3,
    "hint": "Think about the laws of exponents applied to matrix multiplication.",
    "explanation": "The solution states that A^(k+1) = A^k ⋅ A."
  },
  {
    "id": "q9",
    "question": "Proof by cases is a valid method to prove p⇒q only when:",
    "options": [
      "p can be split into cases r, s, t such that p = r ∨ s ∨ t",
      "q can be split into cases r, s, t such that q = r ∨ s ∨ t",
      "The number of cases is infinite",
      "It is impossible to use deductive reasoning"
    ],
    "correct_answer": 1,
    "hint": "The hypothesis must be exhaustive.",
    "explanation": "This method is possible only when p can be split into several exhaustive cases."
  },
  {
    "id": "q10",
    "question": "In Example 4, to prove the projection formula a = bcosC + ccosB, the triangle ABC is split into which three cases?",
    "options": [
      "Isosceles, Scalene, Equilateral",
      "Acute angled, Obtuse angled, Right angled",
      "Small, Medium, Large",
      "Positive area, Negative area, Zero area"
    ],
    "correct_answer": 2,
    "hint": "The classification depends on the angle C.",
    "explanation": "The text splits the proof into cases where angle C is acute, obtuse, or a right angle."
    }
    ]
    },
    {
      "id": "mcq_physics_11_ch1",
      "title": "Physical World - Test",
      "subject": "Physics",
      "class_number": 11,
      "total_questions": 5,
      "time_limit": 5,
      "difficulty": "Medium",
      "thumbnail": "",
      "questions": [
        {
    "id": "q1",
    "question": "संसर्गजन्य रोग (Infectious Diseases) प्रामुख्याने कोणत्या घटकांमुळे होतात?",
    "options": [
      "जीवनशैलीतील बदल",
      "दूषित हवा, पाणी, अन्न किंवा वाहक",
      "अनुवंशिकता",
      "चयापचय क्रियांत बिघाड"
    ],
    "correct_answer": 1,
    "hint": "हे रोग बाह्य माध्यमांमार्फत पसरतात.",
    "explanation": "संसर्गजन्य रोग हे दूषित हवा, पाणी, अन्न किंवा वाहक (कीटक व प्राणी) यांसारख्या बाह्य माध्यमांमार्फत पसरतात."
  },
  {
    "id": "q2",
    "question": "खालीलपैकी कोणते वैशिष्ट्य असंसर्गजन्य रोगांचे (Non-infectious Diseases) आहे?",
    "options": [
      "हे रोग साथीच्या स्वरूपात पसरतात.",
      "हे रोग विशिष्ट सूक्ष्मजीवांमुळे होतात.",
      "हे रोग थेट संपर्कातून एका व्यक्तीकडून दुसऱ्या व्यक्तीकडे पसरत नाहीत.",
      "हे रोग प्रतिजैविकांनी (Antibiotics) बरे होतात."
    ],
    "correct_answer": 2,
    "hint": "हे रोग संक्रामक नसतात.",
    "explanation": "असंसर्गजन्य रोग संसर्गातून किंवा थेट संपर्कातून एका व्यक्तीकडून दुसऱ्या व्यक्तीकडे पसरत नाहीत आणि ते सूक्ष्मजीवांमुळे होत नाहीत."
  },
  {
    "id": "q3",
    "question": "संसर्गजन्य रोगांवर मुख्य उपचार पद्धती कोणती असते?",
    "options": [
      "फिजिओथेरपी",
      "आहार नियंत्रण",
      "प्रतिजैविके (Antibiotics) आणि लस",
      "जीवनशैलीत बदल"
    ],
    "correct_answer": 2,
    "hint": "यामध्ये रोगकारकांना नष्ट करणे अपेक्षित असते.",
    "explanation": "संसर्गजन्य रोगांवर प्रतिजैविके, लस आणि विषाणू-विरोधी औषधे वापरून रोगकारकांना नष्ट करणे हा मुख्य उपचार असतो."
  },
  {
    "id": "q4",
    "question": "खालीलपैकी कोणता रोग 'असंसर्गजन्य' गटात मोडतो?",
    "options": [
      "क्षय (Tuberculosis)",
      "मधुमेह (Diabetes)",
      "इन्फ्लुएन्झा",
      "डेंग्यू"
    ],
    "correct_answer": 1,
    "hint": "हा रोग जीवनशैली किंवा चयापचयाशी संबंधित आहे.",
    "explanation": "मधुमेह हा असंसर्गजन्य रोग आहे, तर क्षय, इन्फ्लुएन्झा आणि डेंग्यू हे संसर्गजन्य आहेत."
  },
  {
    "id": "q5",
    "question": "संसर्गजन्य रोगांचा कालावधी व तीव्रता सामान्यतः कशी असते?",
    "options": [
      "दीर्घकालीन (Chronic)",
      "तीव्र (Acute) आणि कमी काळात बरे होणारे",
      "आयुष्यभर राहणारे",
      "यापैकी नाही"
    ],
    "correct_answer": 1,
    "hint": "हे रोग अचानक उद्भवतात.",
    "explanation": "संसर्गजन्य रोग अनेकदा तीव्र (Acute) स्वरूपाचे असतात आणि औषधोपचाराने कमी काळात बरे होऊ शकतात."
  }
      ]
    }
  ]
}
